{
    "dar" : "abreuver",
    "concordar" : "accorder",
    "comprar" : "acheter",
    "suceder" : "advenir",
    "negocio" : "affaire",
    "ayudar" : "aider",
    "amar" : "aimer",
    "ir" : "aller",
    "iluminar" : "allumer",
    "entonces" : "alors",
    "multa" : "amende",
    "amiga" : "amie intime",
    "amigos" : "amis",
    "apartamento" : "appartement",
    "llamada" : "appel",
    "traer" : "apporter",
    "dinero" : "argent",
    "aspecto" : "aspect",
    "esperar" : "attendre",
    "ninguno" : "aucun",
    "hoy" : "aujourd'hui",
    "tan" : "aussi",
    "otro" : "autre",
    "antes" : "avant",
    "con" : "avec",
    "abogado" : "avocat",
    "haber" : "avoir",
    "necesitar" : "avoir besoin de",
    "cinta" : "bande",
    "hermoso" : "beau",
    "muchos" : "beaucoup",
    "mucho" : "beaucoup",
    "blanco" : "blanc",
    "boca" : "bouche",
    "mover" : "bouger",
    "oficina" : "bureau",
    "quieto" : "calme",
    "poder" : "capable",
    "causa" : "cause",
    "esto" : "ce",
    "esta" : "ce",
    "cien" : "cent",
    "probabilidad" : "chance",
    "suerte" : "chance",
    "fortunado" : "chanceux",
    "cambio" : "changement",
    "cada" : "chaque",
    "cada" : "chaque",
    "perro" : "chien de chasse",
    "cosa" : "chose",
    "cima" : "cime",
    "cinco" : "cinq",
    "club" : "club",
    "caja fuerte" : "coffre-fort",
    "encabezar" : "commander",
    "ordenar" : "commander",
    "como" : "comme",
    "como" : "comme",
    "empresa" : "compagnie",
    "completo" : "complet",
    "entender" : "comprendre",
    "entender" : "comprendre",
    "contar" : "compter",
    "contento" : "content",
    "contra" : "contre",
    "propio" : "convenable",
    "encontrar" : "converger",
    "encontrar" : "converger",
    "cuerpo" : "corps",
    "correcto" : "correct",
    "pareja" : "couple",
    "correr" : "courir",
    "curso" : "cours",
    "tapa" : "couvercle",
    "bailar" : "danser",
    "fecha de nacimiento" : "date de naissance",
    "de" : "de",
    "de" : "de",
    "otra vez" : "de nouveau",
    "pedir" : "demander",
    "desde" : "depuis",
    "dos" : "deux",
    "volver" : "devenir",
    "adivinar" : "deviner",
    "deber" : "devoir",
    "deber" : "devoir",
    "Dios" : "dieu",
    "diez" : "dix",
    "espalda" : "dos",
    "dolor" : "douleur",
    "dulce" : "doux",
    "recto" : "droit",
    "duro" : "dur",
    "agua" : "eau",
    "ella" : "elle",
    "besar" : "embrasser",
    "en realidad" : "en fait",
    "a" : "en train",
    "embarazada" : "enceinte",
    "hijo" : "enfant",
    "hijos" : "enfants",
    "infierno" : "enfer",
    "finalmente" : "enfin",
    "juntos" : "ensemble",
    "enviar" : "envoyer",
    "esperanza" : "espoir",
    "y" : "et",
    "exactamente" : "exactement",
    "explicar" : "expliquer",
    "cara" : "face",
    "actuar" : "faire",
    "hacer" : "faire",
    "error" : "faute",
    "incorrecto" : "faux",
    "favor" : "faveur",
    "esposa" : "femme",
    "mujer" : "femme",
    "mujeres" : "femmes",
    "cerrar" : "fermer",
    "cerrar" : "fermer",
    "orgulloso" : "fier",
    "hija" : "fille",
    "meta" : "fin",
    "terminado" : "fini",
    "acabar" : "finir",
    "fuerte" : "fort",
    "loco/a" : "fou",
    "loco" : "fou",
    "joder" : "foutre",
    "hogar" : "foyer",
    "fresco" : "frais",
    "futuro" : "futur",
    "ganar" : "gagner",
    "hielo" : "glace",
    "gota" : "goutte",
    "grande" : "grand",
    "guerra" : "guerre",
    "escuchar" : "guetter",
    "conducir" : "guider",
    "vestir" : "habiller",
    "hora" : "heure",
    "hora" : "heure",
    "feliz" : "heureux",
    "historia" : "historique",
    "honor" : "honneur",
    "fuera" : "hors",
    "ocho" : "huit",
    "humano" : "humain",
    "hace" : "il y a",
    "ellos" : "ils",
    "imagen" : "image",
    "malo" : "immoral",
    "malo" : "immoral",
    "importante" : "important",
    "incendio" : "incendie",
    "momento" : "instant",
    "momento" : "instant",
    "nunca" : "jamais",
    "yo" : "je",
    "yo" : "je",
    "juego" : "jeu",
    "guapo" : "joli",
    "jugar" : "jouer",
    "tocar" : "jouer",
    "blasfemar" : "jurer",
    "hasta" : "jusqu'ici",
    "hasta" : "jusqu'ici",
    "lo peor" : "le pire",
    "ambos" : "les deux",
    "libre" : "libre",
    "leer" : "lire",
    "cama" : "lit",
    "libro" : "livre",
    "ley" : "loi",
    "lejano" : "lointain",
    "mientras" : "lorsque",
    "mayo" : "mai",
    "ahora" : "maintenant",
    "pero" : "mais",
    "casa" : "maison",
    "mal" : "mal",
    "enfermo" : "malade",
    "comer" : "manger",
    "errar" : "manquer",
    "caminar" : "marcher",
    "marido" : "mari",
    "boda" : "mariage",
    "marca" : "marque",
    "obrero" : "matelot",
    "me" : "me",
    "mejor" : "meilleur",
    "mentira" : "mensonge",
    "gracias" : "merci",
    "maravilloso" : "merveilleux",
    "mensaje" : "message",
    "colocar" : "mettre",
    "asesinato" : "meurtre",
    "lindo" : "mignon",
    "mil" : "mille",
    "minuto" : "minute",
    "Sra" : "Mme",
    "mi" : "mon",
    "pasear" : "monter",
    "mostrar" : "montrer",
    "pieza" : "morceau",
    "muerto" : "mort",
    "muerte" : "mort",
    "palabra" : "mot",
    "morir" : "mourir",
    "nada" : "ne",
    "cualquier" : "n'importe quel",
    "negro" : "noir",
    "no" : "non",
    "normal" : "normal",
    "nuestro" : "notre",
    "alimento" : "nourriture",
    "nosotros" : "nous",
    "nuevo" : "nouveau",
    "noticias" : "nouvelles",
    "oscuridad" : "nuit",
    "ofrecer" : "offrir",
    "se" : "on",
    "o" : "ou",
    "abierto" : "ouvert",
    "papel" : "papier",
    "porque" : "parce que",
    "padres" : "parents",
    "a veces" : "parfois",
    "hablar" : "parler",
    "hablar" : "parler",
    "entre" : "parmi",
    "parte" : "partie",
    "gastar" : "passer",
    "pobre" : "pauvre",
    "pagar" : "payer",
    "pena" : "peine",
    "suponer" : "penser",
    "pensar" : "penser",
    "perder" : "perdre",
    "figura" : "personnage",
    "nadie" : "personne",
    "personaje" : "personne",
    "personal" : "personnel",
    "novio" : "petit ami",
    "novio" : "petit ami",
    "poco" : "peu",
    "peor" : "pire",
    "plan" : "plan",
    "colocado" : "planer",
    "pelo" : "poil",
    "punto" : "point",
    "puerta" : "porte",
    "llevar" : "porter",
    "posible" : "possible",
    "primero" : "premier",
    "tomar" : "prendre",
    "aumentar su valor" : "prendre de la valeur",
    "casi" : "presque",
    "probablemente" : "probablement",
    "cerca" : "proche",
    "cerca" : "proche",
    "prometer" : "promettre",
    "probar" : "prouver",
    "dicho" : "proverbe",
    "aljibe" : "puits",
    "el" : "quand",
    "el" : "quand",
    "cuando" : "quand",
    "cuatro" : "quatre",
    "que" : "que",
    "algo" : "quelque chose",
    "algunos" : "quelques",
    "alguien" : "quelqu'un",
    "alguien" : "quelqu'un",
    "pregunta" : "question",
    "quien" : "qui",
    "decir" : "raconter",
    "decir" : "raconter",
    "raya" : "raie",
    "agradecer" : "reconnaissant",
    "regalar" : "regaler",
    "mirar" : "regarder",
    "ver" : "regarder",
    "respecto" : "respect",
    "sentir" : "ressentir",
    "resto" : "reste",
    "mantenerse" : "rester",
    "retener" : "retenir",
    "montar" : "rouler",
    "calle" : "rue",
    "hola" : "salut",
    "sangre" : "sang",
    "sin" : "sans",
    "saber" : "savoir",
    "sierra" : "scie",
    "pelear" : "se battre",
    "preguntarse" : "se demander",
    "romper" : "se rompre",
    "secreto" : "secret",
    "semana" : "semaine",
    "parecer" : "sembler",
    "sentimiento" : "sentiment",
    "siete" : "sept",
    "solitario" : "seul",
    "sexo" : "sexe",
    "si" : "si",
    "si" : "si",
    "signo" : "signe",
    "simple" : "simple",
    "seis" : "six",
    "piso" : "sol",
    "piso" : "sol",
    "su" : "son",
    "su" : "son",
    "sonar" : "sonner",
    "sonar" : "sonner",
    "salir" : "sortir",
    "desear" : "souhaiter",
    "desear" : "souhaiter",
    "bajo" : "sous",
    "estoy" : "suis",
    "seguir" : "suivre",
    "materia" : "sujet",
    "materia" : "sujet",
    "sorpresa" : "surprise",
    "tabla" : "tableau",
    "aunque" : "tandis que",
    "terrible" : "terrible",
    "testamento" : "testament",
    "tirar" : "tirer",
    "tirar" : "tirer",
    "todo" : "tout",
    "todos" : "tout le monde",
    "trabajo" : "travail",
    "demasiado" : "trop",
    "matar" : "tuer",
    "tipo" : "type",
    "un" : "un",
    "una" : "une",
    "usar" : "utiliser",
    "valor" : "valeur",
    "venir" : "venir",
    "acabar de" : "venir de",
    "bebida" : "verre",
    "vida" : "vie",
    "anciano" : "vieux",
    "municipal" : "ville",
    "ciudad" : "ville",
    "veinte" : "vingt",
    "vivo" : "vivant",
    "camino" : "voie",
    "querer" : "vouloir dire",
    "viaje" : "voyage",
    "verdaderamente" : "vraiment",
}