{
    "acero" : "acciaio",
    "acusar" : "accusare",
    "agresivo" : "aggressivo",
    "aguja" : "ago",
    "agosto" : "agosto",
    "coartada" : "alibi",
    "altar" : "altare",
    "altura" : "altezza",
    "ambiente" : "ambiente",
    "ahogarse" : "annegarsi",
    "aburrido" : "annoiato",
    "abril" : "aprile",
    "langosta" : "aragosta",
    "arbusto" : "arbusto",
    "rendirse" : "arrendersi",
    "arrogante" : "arrogante",
    "aspirina" : "aspirina",
    "as" : "asso",
    "absurdo" : "assurdo",
    "subasta" : "asta",
    "actriz" : "attrice",
    "actualmente" : "attualmente",
    "barba" : "barba",
    "blanco" : "bianco",
    "Biblia" : "Bibbia",
    "travieso" : "birichino",
    "biftec" : "bistecca",
    "bomba" : "bomba",
    "bosque" : "bosco",
    "perezoso" : "bradipo",
    "brillar" : "brillare",
    "sangrar" : "buttare sangue",
    "perseguir" : "cacciare",
    "cazador" : "cacciatore",
    "calendario" : "calendario",
    "calvo" : "calvo",
    "vela" : "candela",
    "candidato" : "candidato",
    "caos" : "caos",
    "cabra" : "capra",
    "carro" : "carro",
    "accidentalmente" : "casualmente",
    "caballo" : "cavallo",
    "tobillo" : "caviglia",
    "cena" : "cena",
    "centavo" : "centesimo",
    "buscar" : "cercare",
    "ciervo" : "cervo",
    "guitarra" : "chitarra",
    "cicatriz" : "cicatrice",
    "cerezo" : "ciliegio",
    "cementerio" : "cimitero",
    "cerca" : "circa",
    "cola" : "coda",
    "cobarde" : "codardo",
    "collar" : "collana",
    "enlace" : "collegamento",
    "incluir" : "comprendere",
    "frontera" : "confine",
    "conejo" : "coniglio",
    "contenido" : "contenuto",
    "conveniente" : "conveniente",
    "viento" : "corno",
    "coro" : "coro",
    "corona" : "corona",
    "consciente" : "cosciente",
    "costa" : "costa",
    "cristal" : "cristallo",
    "crudo" : "crudo",
    "cuchara" : "cucchiaio",
    "cachorro" : "cucciolo",
    "cocinado" : "cucinato",
    "cultura" : "cultura",
    "cuero" : "cuoio",
    "diosa" : "dea",
    "debilidad" : "debolezza",
    "diente" : "dente",
    "dentista" : "dentista",
    "diecinueve" : "diciannove",
    "diecisiete" : "diciassette",
    "elefante" : "elefante",
    "afecto" : "emozione",
    "pasto" : "erba",
    "brezo" : "erica",
    "existencia" : "esistenza",
    "etiqueta" : "etichetta",
    "acto" : "fatto",
    "fiebre" : "febbre",
    "flama" : "fiamma",
    "bastos" : "fiori",
    "hoja" : "foglia",
    "locura" : "follia",
    "horno" : "forno",
    "afortunadamente" : "fortunatamente",
    "frente" : "fronte",
    "gallo" : "gallo",
    "gato" : "gatto",
    "gen" : "gene",
    "arrendajo" : "ghiandaia",
    "adolescente" : "giovincello",
    "junio" : "giugno",
    "selva" : "giungla",
    "juramento" : "giuramento",
    "juramento" : "giuramento",
    "hincharse" : "gonfiare",
    "falda" : "gonna",
    "griego" : "greco",
    "grifo" : "grifone",
    "gris" : "grigio",
    "vado" : "guado",
    "mejilla" : "guancia",
    "guerrero" : "guerriero",
    "pasatiempo" : "hobby",
    "ignoto" : "ignoto",
    "inmediato" : "immediato",
    "impedir" : "impedire",
    "Imperio" : "impero",
    "incendio" : "incendio",
    "animar" : "incoraggiare",
    "independiente" : "indipendente",
    "inevitable" : "inevitabile",
    "insignificante" : "insignificante",
    "envidia" : "invidia",
    "invisible" : "invisibile",
    "bluejeans" : "jeans",
    "cuchilla" : "lama",
    "latino" : "latino",
    "lamer" : "leccare",
    "lesbiana" : "lesbica",
    "herida" : "lesione",
    "lucha" : "lotta",
    "lucha libre" : "lotta libera",
    "pulir" : "lucidare",
    "julio" : "luglio",
    "hechicero" : "mago",
    "cerdo" : "maiale",
    "enfermedad" : "malattia",
    "marina" : "marina",
    "marinero" : "marinaio",
    "marioneta" : "marionetta",
    "martillo" : "martello",
    "masticar" : "masticare",
    "ladrillo" : "mattone",
    "menos" : "meno",
    "menta" : "menta",
    "barbilla" : "mento",
    "mensajero" : "messaggero",
    "metal" : "metallo",
    "rompecabezas" : "mistero",
    "moderno" : "moderno",
    "motocicleta" : "motocicletta",
    "motor" : "motore",
    "movimiento" : "movimento",
    "molino" : "mulino",
    "momia" : "mummia",
    "mutuo" : "mutuo",
    "niebla" : "nebbia",
    "cueva" : "nido",
    "noveno" : "nono",
    "alma" : "nucleo",
    "nube" : "nuvola",
    "objetivo" : "obbiettivo",
    "honor" : "onore",
    "operar" : "operare",
    "octavo" : "ottavo",
    "pago" : "pagamento",
    "espada" : "pala",
    "globo" : "palloncino",
    "palmera" : "palma",
    "tocino" : "pancetta",
    "barriga" : "pancia",
    "panadero" : "panettiere",
    "desfile" : "parata",
    "peluca" : "parrucca",
    "pasaporte" : "passaporto",
    "masa" : "pasta",
    "papa" : "patata",
    "oveja" : "pecora",
    "pene" : "pene",
    "plaga" : "peste",
    "chisme" : "pettegolezzo",
    "petirrojo" : "pettirosso",
    "pecho" : "petto",
    "plato" : "piatto",
    "plegar" : "piegare",
    "pila" : "pila",
    "poco profundo" : "poco profondo",
    "poema" : "poema",
    "poeta" : "poeta",
    "pulgar" : "pollice",
    "polvo" : "polvere",
    "morado" : "porpora",
    "puerto" : "porto",
    "preciso" : "preciso",
    "presidente" : "presidente",
    "previo" : "previo",
    "primario" : "primario",
    "principal" : "principale",
    "principio" : "principio",
    "privilegio" : "privilegio",
    "sin valor" : "privo di valore",
    "producir" : "produrre",
    "ganancia" : "profitto",
    "aroma" : "profumo",
    "prohibir" : "proibire",
    "nieta" : "pronipote",
    "protestar" : "protestare",
    "proa" : "prua",
    "punto" : "puntino",
    "puro" : "puro",
    "recibo" : "quietanza",
    "como resultado" : "quindi",
    "diario" : "quotidiano",
    "rabia" : "rabbia",
    "recomendar" : "raccomandare",
    "afeitar" : "radere",
    "novio" : "ragazzo",
    "rana" : "rana",
    "ajustador" : "reggipetto",
    "registrar" : "registrare",
    "relativo" : "relativo",
    "residencia" : "residenza",
    "receta" : "ricetta",
    "recibir" : "ricevere",
    "referir" : "riferire",
    "arroz" : "riso",
    "ritual" : "rituale",
    "revelar" : "rivelare",
    "novela" : "romanzo",
    "golondrina" : "rondine",
    "acantilado" : "rupe",
    "bolsa" : "sacco",
    "ensayo" : "saggio",
    "salario" : "salario",
    "salto" : "salto",
    "ajedrez" : "scacchi",
    "escalera" : "scala",
    "escala" : "scala",
    "soltero" : "scapolone",
    "bufanda" : "sciarpa",
    "derretir" : "sciogliere",
    "derrota" : "sconfitta",
    "reventar" : "scoppiare",
    "descubrir" : "scoprire",
    "escudo" : "scudo",
    "balde" : "secchio",
    "sexto" : "sesto",
    "seda" : "seta",
    "sello" : "sigillo",
    "suma" : "somma",
    "sobre" : "sopra",
    "sordo" : "sordo",
    "barrer" : "spazzare",
    "especie" : "specie",
    "charca" : "stagno",
    "estatua" : "statua",
    "planchar" : "stirare",
    "bota" : "stivale",
    "extraordinario" : "straordinario",
    "estrecho" : "stretto",
    "monja" : "suora",
    "superior" : "superiore",
    "corte de pelo" : "taglio",
    "soborno" : "tangente",
    "alfombra" : "tappeto",
    "honorario" : "tassa",
    "tatuaje" : "tatuaggio",
    "pote" : "teglia",
    "templo" : "tempio",
    "tienda" : "tenda",
    "tierno" : "tenero",
    "techo" : "tetto",
    "tonelada" : "tonnellata",
    "toser" : "tossire",
    "puesta del sol" : "tramonto",
    "transportar" : "trasportare",
    "trece" : "tredici",
    "maleta" : "valigia",
    "viuda" : "vedova",
    "vendedor" : "venditore",
    "gusano" : "verme",
    "avenida" : "viale",
    "vital" : "vitale",
    "garrapata" : "zecca",
    "jengibre" : "zenzero",
    "calabaza" : "zucca",
}